{
    "version": "4.5.7",
    "flags": {},
    "shapes": [
        {
            "label": "abdomen",
            "points": [
                [
                    1984.4979839999999,
                    1116.79872
                ],
                [
                    1978.1999999999998,
                    1123.10064
                ],
                [
                    1959.297984,
                    1123.10064
                ],
                [
                    1953.0,
                    1129.39952
                ],
                [
                    1946.6979840000001,
                    1129.39952
                ],
                [
                    1940.4,
                    1135.7014399999998
                ],
                [
                    1921.4979839999999,
                    1135.7014399999998
                ],
                [
                    1915.1999999999998,
                    1142.0003199999999
                ],
                [
                    1908.897984,
                    1142.0003199999999
                ],
                [
                    1902.6,
                    1148.2992
                ],
                [
                    1896.297984,
                    1148.2992
                ],
                [
                    1877.4,
                    1167.19888
                ],
                [
                    1871.097984,
                    1167.19888
                ],
                [
                    1864.8000000000002,
                    1173.5008
                ],
                [
                    1864.8000000000002,
                    1179.79968
                ],
                [
                    1845.897984,
                    1198.69936
                ],
                [
                    1845.897984,
                    1205.00128
                ],
                [
                    1839.6,
                    1211.30016
                ],
                [
                    1839.6,
                    1400.3
                ],
                [
                    1845.897984,
                    1406.59888
                ],
                [
                    1845.897984,
                    1419.19968
                ],
                [
                    1858.4979839999999,
                    1431.8004799999999
                ],
                [
                    1858.4979839999999,
                    1444.40128
                ],
                [
                    1896.297984,
                    1482.20064
                ],
                [
                    1896.297984,
                    1494.80144
                ],
                [
                    1908.897984,
                    1507.3992
                ],
                [
                    1908.897984,
                    1513.70112
                ],
                [
                    1927.8000000000002,
                    1532.6008
                ],
                [
                    1940.4,
                    1532.6008
                ],
                [
                    1946.6979840000001,
                    1538.89968
                ],
                [
                    1953.0,
                    1538.89968
                ],
                [
                    1959.297984,
                    1545.19856
                ],
                [
                    1965.6,
                    1545.19856
                ],
                [
                    1971.897984,
                    1551.50048
                ],
                [
                    1978.1999999999998,
                    1551.50048
                ],
                [
                    1997.097984,
                    1570.4001600000001
                ],
                [
                    2003.4,
                    1570.4001600000001
                ],
                [
                    2022.2979839999998,
                    1589.2998400000001
                ],
                [
                    2028.6000000000001,
                    1589.2998400000001
                ],
                [
                    2060.097984,
                    1620.80032
                ],
                [
                    2066.3999999999996,
                    1620.80032
                ],
                [
                    2072.697984,
                    1627.0991999999999
                ],
                [
                    2072.697984,
                    1633.40112
                ],
                [
                    2079.0,
                    1633.40112
                ],
                [
                    2097.897984,
                    1652.3008
                ],
                [
                    2104.2,
                    1652.3008
                ],
                [
                    2123.097984,
                    1671.2004800000002
                ],
                [
                    2129.3999999999996,
                    1671.2004800000002
                ],
                [
                    2148.297984,
                    1690.1001599999997
                ],
                [
                    2154.6000000000004,
                    1690.1001599999997
                ],
                [
                    2179.8,
                    1715.2987200000002
                ],
                [
                    2179.8,
                    1721.60064
                ],
                [
                    2192.3999999999996,
                    1734.1984
                ],
                [
                    2192.3999999999996,
                    1740.5003199999999
                ],
                [
                    2217.6000000000004,
                    1765.69888
                ],
                [
                    2217.6000000000004,
                    1772.0008000000003
                ],
                [
                    2230.2,
                    1784.59856
                ],
                [
                    2230.2,
                    1790.90048
                ],
                [
                    2236.502016,
                    1797.19936
                ],
                [
                    2236.502016,
                    1803.5012800000002
                ],
                [
                    2242.8,
                    1809.80016
                ],
                [
                    2242.8,
                    1816.0990399999998
                ],
                [
                    2268.0,
                    1841.30064
                ],
                [
                    2274.297984,
                    1841.30064
                ],
                [
                    2286.897984,
                    1853.90144
                ],
                [
                    2293.2,
                    1853.90144
                ],
                [
                    2299.497984,
                    1860.20032
                ],
                [
                    2305.8,
                    1860.20032
                ],
                [
                    2312.097984,
                    1866.4992
                ],
                [
                    2318.3999999999996,
                    1866.4992
                ],
                [
                    2337.297984,
                    1885.39888
                ],
                [
                    2343.6000000000004,
                    1885.39888
                ],
                [
                    2356.2,
                    1897.99968
                ],
                [
                    2362.502016,
                    1897.99968
                ],
                [
                    2394.0,
                    1929.50016
                ],
                [
                    2400.297984,
                    1929.50016
                ],
                [
                    2406.6000000000004,
                    1935.79904
                ],
                [
                    2419.2,
                    1935.79904
                ],
                [
                    2425.497984,
                    1942.10096
                ],
                [
                    2438.097984,
                    1942.10096
                ],
                [
                    2444.3999999999996,
                    1948.3998399999998
                ],
                [
                    2450.697984,
                    1948.3998399999998
                ],
                [
                    2457.0,
                    1954.69872
                ],
                [
                    2463.297984,
                    1954.69872
                ],
                [
                    2469.6000000000004,
                    1961.00064
                ],
                [
                    2482.2,
                    1961.00064
                ],
                [
                    2488.502016,
                    1967.29952
                ],
                [
                    2501.097984,
                    1967.29952
                ],
                [
                    2507.3999999999996,
                    1973.5983999999999
                ],
                [
                    2513.697984,
                    1973.5983999999999
                ],
                [
                    2520.0,
                    1979.9003199999997
                ],
                [
                    2526.297984,
                    1979.9003199999997
                ],
                [
                    2532.6000000000004,
                    1986.1992
                ],
                [
                    2633.3999999999996,
                    1986.1992
                ],
                [
                    2633.3999999999996,
                    1954.69872
                ],
                [
                    2627.097984,
                    1948.3998399999998
                ],
                [
                    2627.097984,
                    1923.20128
                ],
                [
                    2633.3999999999996,
                    1916.89936
                ],
                [
                    2633.3999999999996,
                    1784.59856
                ],
                [
                    2627.097984,
                    1778.29968
                ],
                [
                    2627.097984,
                    1759.3999999999999
                ],
                [
                    2620.8,
                    1753.10112
                ],
                [
                    2620.8,
                    1740.5003199999999
                ],
                [
                    2614.502016,
                    1734.1984
                ],
                [
                    2614.502016,
                    1721.60064
                ],
                [
                    2601.897984,
                    1708.99984
                ],
                [
                    2601.897984,
                    1702.7009600000001
                ],
                [
                    2595.6000000000004,
                    1696.39904
                ],
                [
                    2595.6000000000004,
                    1690.1001599999997
                ],
                [
                    2589.297984,
                    1683.80128
                ],
                [
                    2589.297984,
                    1671.2004800000002
                ],
                [
                    2583.0,
                    1664.89856
                ],
                [
                    2583.0,
                    1652.3008
                ],
                [
                    2576.697984,
                    1645.99888
                ],
                [
                    2576.697984,
                    1633.40112
                ],
                [
                    2570.3999999999996,
                    1627.0991999999999
                ],
                [
                    2570.3999999999996,
                    1614.4984000000002
                ],
                [
                    2564.097984,
                    1608.19952
                ],
                [
                    2564.097984,
                    1576.69904
                ],
                [
                    2557.8,
                    1570.4001600000001
                ],
                [
                    2557.8,
                    1551.50048
                ],
                [
                    2551.497984,
                    1545.19856
                ],
                [
                    2551.497984,
                    1538.89968
                ],
                [
                    2545.2,
                    1532.6008
                ],
                [
                    2545.2,
                    1526.2988799999998
                ],
                [
                    2538.897984,
                    1520.0
                ],
                [
                    2538.897984,
                    1513.70112
                ],
                [
                    2532.6000000000004,
                    1507.3992
                ],
                [
                    2532.6000000000004,
                    1501.10032
                ],
                [
                    2520.0,
                    1488.49952
                ],
                [
                    2520.0,
                    1482.20064
                ],
                [
                    2507.3999999999996,
                    1469.5998399999999
                ],
                [
                    2507.3999999999996,
                    1463.30096
                ],
                [
                    2488.502016,
                    1444.40128
                ],
                [
                    2488.502016,
                    1438.09936
                ],
                [
                    2469.6000000000004,
                    1419.19968
                ],
                [
                    2469.6000000000004,
                    1412.9008000000001
                ],
                [
                    2463.297984,
                    1406.59888
                ],
                [
                    2463.297984,
                    1400.3
                ],
                [
                    2444.3999999999996,
                    1381.40032
                ],
                [
                    2444.3999999999996,
                    1375.1014400000001
                ],
                [
                    2431.8,
                    1362.50064
                ],
                [
                    2431.8,
                    1356.19872
                ],
                [
                    2412.897984,
                    1337.2990399999999
                ],
                [
                    2412.897984,
                    1331.00016
                ],
                [
                    2387.697984,
                    1305.79856
                ],
                [
                    2387.697984,
                    1299.49968
                ],
                [
                    2362.502016,
                    1274.30112
                ],
                [
                    2362.502016,
                    1267.9992
                ],
                [
                    2356.2,
                    1261.70032
                ],
                [
                    2349.897984,
                    1261.70032
                ],
                [
                    2343.6000000000004,
                    1255.3984
                ],
                [
                    2343.6000000000004,
                    1249.09952
                ],
                [
                    2337.297984,
                    1242.80064
                ],
                [
                    2331.0,
                    1242.80064
                ],
                [
                    2312.097984,
                    1223.90096
                ],
                [
                    2312.097984,
                    1217.59904
                ],
                [
                    2286.897984,
                    1192.40048
                ],
                [
                    2280.6000000000004,
                    1192.40048
                ],
                [
                    2274.297984,
                    1186.0985600000001
                ],
                [
                    2261.697984,
                    1186.0985600000001
                ],
                [
                    2255.3999999999996,
                    1179.79968
                ],
                [
                    2249.097984,
                    1179.79968
                ],
                [
                    2242.8,
                    1173.5008
                ],
                [
                    2236.502016,
                    1173.5008
                ],
                [
                    2230.2,
                    1167.19888
                ],
                [
                    2217.6000000000004,
                    1167.19888
                ],
                [
                    2211.297984,
                    1160.9
                ],
                [
                    2205.0,
                    1160.9
                ],
                [
                    2198.697984,
                    1154.60112
                ],
                [
                    2192.3999999999996,
                    1154.60112
                ],
                [
                    2186.097984,
                    1148.2992
                ],
                [
                    2179.8,
                    1148.2992
                ],
                [
                    2173.497984,
                    1142.0003199999999
                ],
                [
                    2167.2,
                    1142.0003199999999
                ],
                [
                    2160.897984,
                    1135.7014399999998
                ],
                [
                    2154.6000000000004,
                    1135.7014399999998
                ],
                [
                    2142.0,
                    1123.10064
                ],
                [
                    2116.8,
                    1123.10064
                ],
                [
                    2110.502016,
                    1116.79872
                ]
            ],
            "group_id": 1,
            "shape_type": "polygon",
            "flags": {}
        },
        {
            "label": "thorax",
            "points": [
                [
                    1379.6979840000001,
                    637.99872
                ],
                [
                    1373.4,
                    644.3006399999999
                ],
                [
                    1360.8000000000002,
                    644.3006399999999
                ],
                [
                    1348.1999999999998,
                    656.90144
                ],
                [
                    1341.897984,
                    656.90144
                ],
                [
                    1335.6,
                    663.2003199999999
                ],
                [
                    1329.297984,
                    663.2003199999999
                ],
                [
                    1323.0,
                    669.4992
                ],
                [
                    1316.6979840000001,
                    669.4992
                ],
                [
                    1316.6979840000001,
                    675.80112
                ],
                [
                    1310.4,
                    682.1
                ],
                [
                    1310.4,
                    688.3988800000001
                ],
                [
                    1304.097984,
                    694.7008
                ],
                [
                    1304.097984,
                    700.99968
                ],
                [
                    1291.4979839999999,
                    713.60048
                ],
                [
                    1291.4979839999999,
                    726.20128
                ],
                [
                    1285.1999999999998,
                    732.50016
                ],
                [
                    1285.1999999999998,
                    757.69872
                ],
                [
                    1278.897984,
                    764.00064
                ],
                [
                    1278.897984,
                    770.29952
                ],
                [
                    1272.6,
                    776.60144
                ],
                [
                    1272.6,
                    795.50112
                ],
                [
                    1266.297984,
                    801.8
                ],
                [
                    1266.297984,
                    839.5993599999999
                ],
                [
                    1260.0,
                    845.9012799999999
                ],
                [
                    1260.0,
                    921.4999999999999
                ],
                [
                    1253.6979840000001,
                    927.7988799999999
                ],
                [
                    1253.6979840000001,
                    990.79984
                ],
                [
                    1247.4,
                    997.09872
                ],
                [
                    1247.4,
                    1034.90112
                ],
                [
                    1253.6979840000001,
                    1041.2
                ],
                [
                    1253.6979840000001,
                    1047.4988799999999
                ],
                [
                    1260.0,
                    1047.4988799999999
                ],
                [
                    1266.297984,
                    1053.8008
                ],
                [
                    1272.6,
                    1053.8008
                ],
                [
                    1278.897984,
                    1047.4988799999999
                ],
                [
                    1291.4979839999999,
                    1047.4988799999999
                ],
                [
                    1297.8000000000002,
                    1041.2
                ],
                [
                    1323.0,
                    1041.2
                ],
                [
                    1329.297984,
                    1047.4988799999999
                ],
                [
                    1335.6,
                    1047.4988799999999
                ],
                [
                    1360.8000000000002,
                    1072.70048
                ],
                [
                    1360.8000000000002,
                    1078.99936
                ],
                [
                    1379.6979840000001,
                    1097.89904
                ],
                [
                    1379.6979840000001,
                    1110.49984
                ],
                [
                    1386.0,
                    1116.79872
                ],
                [
                    1386.0,
                    1129.39952
                ],
                [
                    1398.6,
                    1142.0003199999999
                ],
                [
                    1398.6,
                    1198.69936
                ],
                [
                    1392.297984,
                    1205.00128
                ],
                [
                    1367.097984,
                    1205.00128
                ],
                [
                    1360.8000000000002,
                    1198.69936
                ],
                [
                    1310.4,
                    1198.69936
                ],
                [
                    1304.097984,
                    1205.00128
                ],
                [
                    1297.8000000000002,
                    1205.00128
                ],
                [
                    1291.4979839999999,
                    1198.69936
                ],
                [
                    1278.897984,
                    1198.69936
                ],
                [
                    1272.6,
                    1192.40048
                ],
                [
                    1260.0,
                    1192.40048
                ],
                [
                    1247.4,
                    1179.79968
                ],
                [
                    1247.4,
                    1186.0985600000001
                ],
                [
                    1241.097984,
                    1192.40048
                ],
                [
                    1241.097984,
                    1274.30112
                ],
                [
                    1247.4,
                    1280.6000000000001
                ],
                [
                    1247.4,
                    1299.49968
                ],
                [
                    1278.897984,
                    1331.00016
                ],
                [
                    1285.1999999999998,
                    1331.00016
                ],
                [
                    1297.8000000000002,
                    1343.60096
                ],
                [
                    1304.097984,
                    1343.60096
                ],
                [
                    1310.4,
                    1349.89984
                ],
                [
                    1373.4,
                    1349.89984
                ],
                [
                    1379.6979840000001,
                    1343.60096
                ],
                [
                    1404.897984,
                    1343.60096
                ],
                [
                    1411.1999999999998,
                    1337.2990399999999
                ],
                [
                    1430.097984,
                    1337.2990399999999
                ],
                [
                    1436.4,
                    1331.00016
                ],
                [
                    1467.897984,
                    1331.00016
                ],
                [
                    1486.8000000000002,
                    1349.89984
                ],
                [
                    1486.8000000000002,
                    1362.50064
                ],
                [
                    1493.097984,
                    1368.79952
                ],
                [
                    1493.097984,
                    1419.19968
                ],
                [
                    1499.4,
                    1425.49856
                ],
                [
                    1512.0,
                    1425.49856
                ],
                [
                    1518.297984,
                    1431.8004799999999
                ],
                [
                    1612.8000000000002,
                    1431.8004799999999
                ],
                [
                    1619.097984,
                    1425.49856
                ],
                [
                    1631.6979840000001,
                    1425.49856
                ],
                [
                    1644.297984,
                    1412.9008000000001
                ],
                [
                    1644.297984,
                    1406.59888
                ],
                [
                    1650.6,
                    1400.3
                ],
                [
                    1650.6,
                    1381.40032
                ],
                [
                    1694.6979840000001,
                    1337.2990399999999
                ],
                [
                    1701.0,
                    1337.2990399999999
                ],
                [
                    1719.897984,
                    1318.3993600000001
                ],
                [
                    1726.1999999999998,
                    1318.3993600000001
                ],
                [
                    1732.5020160000001,
                    1312.10048
                ],
                [
                    1738.8000000000002,
                    1312.10048
                ],
                [
                    1776.6,
                    1274.30112
                ],
                [
                    1776.6,
                    1267.9992
                ],
                [
                    1801.8000000000002,
                    1242.80064
                ],
                [
                    1801.8000000000002,
                    1236.49872
                ],
                [
                    1820.6979840000001,
                    1217.59904
                ],
                [
                    1820.6979840000001,
                    1211.30016
                ],
                [
                    1833.297984,
                    1198.69936
                ],
                [
                    1833.297984,
                    1192.40048
                ],
                [
                    1839.6,
                    1186.0985600000001
                ],
                [
                    1845.897984,
                    1186.0985600000001
                ],
                [
                    1852.1999999999998,
                    1179.79968
                ],
                [
                    1852.1999999999998,
                    1173.5008
                ],
                [
                    1864.8000000000002,
                    1160.9
                ],
                [
                    1871.097984,
                    1160.9
                ],
                [
                    1877.4,
                    1154.60112
                ],
                [
                    1890.0,
                    1154.60112
                ],
                [
                    1902.6,
                    1142.0003199999999
                ],
                [
                    1902.6,
                    1085.3012800000001
                ],
                [
                    1896.297984,
                    1078.99936
                ],
                [
                    1871.097984,
                    1078.99936
                ],
                [
                    1864.8000000000002,
                    1072.70048
                ],
                [
                    1795.4979839999999,
                    1072.70048
                ],
                [
                    1789.1999999999998,
                    1066.39856
                ],
                [
                    1751.4,
                    1066.39856
                ],
                [
                    1745.097984,
                    1060.09968
                ],
                [
                    1738.8000000000002,
                    1060.09968
                ],
                [
                    1719.897984,
                    1041.2
                ],
                [
                    1713.6,
                    1041.2
                ],
                [
                    1707.297984,
                    1034.90112
                ],
                [
                    1701.0,
                    1034.90112
                ],
                [
                    1656.897984,
                    990.79984
                ],
                [
                    1656.897984,
                    978.19904
                ],
                [
                    1650.6,
                    971.9001599999999
                ],
                [
                    1650.6,
                    965.6012800000001
                ],
                [
                    1638.0,
                    953.00048
                ],
                [
                    1638.0,
                    946.69856
                ],
                [
                    1631.6979840000001,
                    940.39968
                ],
                [
                    1631.6979840000001,
                    921.4999999999999
                ],
                [
                    1625.4,
                    915.2011200000001
                ],
                [
                    1625.4,
                    889.99952
                ],
                [
                    1619.097984,
                    883.7006399999999
                ],
                [
                    1619.097984,
                    852.20016
                ],
                [
                    1625.4,
                    845.9012799999999
                ],
                [
                    1625.4,
                    833.3004800000001
                ],
                [
                    1631.6979840000001,
                    826.9985599999999
                ],
                [
                    1631.6979840000001,
                    808.09888
                ],
                [
                    1638.0,
                    801.8
                ],
                [
                    1638.0,
                    795.50112
                ],
                [
                    1656.897984,
                    776.60144
                ],
                [
                    1656.897984,
                    770.29952
                ],
                [
                    1675.8000000000002,
                    751.39984
                ],
                [
                    1675.8000000000002,
                    745.10096
                ],
                [
                    1694.6979840000001,
                    726.20128
                ],
                [
                    1694.6979840000001,
                    719.89936
                ],
                [
                    1701.0,
                    713.60048
                ],
                [
                    1701.0,
                    707.2985600000001
                ],
                [
                    1707.297984,
                    700.99968
                ],
                [
                    1707.297984,
                    694.7008
                ],
                [
                    1701.0,
                    688.3988800000001
                ],
                [
                    1701.0,
                    682.1
                ],
                [
                    1694.6979840000001,
                    675.80112
                ],
                [
                    1688.4,
                    675.80112
                ],
                [
                    1682.097984,
                    669.4992
                ],
                [
                    1669.4979839999999,
                    669.4992
                ],
                [
                    1663.1999999999998,
                    663.2003199999999
                ],
                [
                    1656.897984,
                    663.2003199999999
                ],
                [
                    1650.6,
                    656.90144
                ],
                [
                    1631.6979840000001,
                    656.90144
                ],
                [
                    1625.4,
                    650.59952
                ],
                [
                    1619.097984,
                    650.59952
                ],
                [
                    1612.8000000000002,
                    644.3006399999999
                ],
                [
                    1587.6,
                    644.3006399999999
                ],
                [
                    1581.297984,
                    637.99872
                ]
            ],
            "group_id": 2,
            "shape_type": "polygon",
            "flags": {}
        },
        {
            "label": "head",
            "points": [
                [
                    1058.4,
                    511.99983999999995
                ],
                [
                    1052.097984,
                    518.29872
                ],
                [
                    1039.4979839999999,
                    518.29872
                ],
                [
                    1026.902016,
                    530.8995199999999
                ],
                [
                    1020.5999999999999,
                    530.8995199999999
                ],
                [
                    1014.3020159999999,
                    537.20144
                ],
                [
                    970.2,
                    537.20144
                ],
                [
                    963.897984,
                    543.50032
                ],
                [
                    938.697984,
                    543.50032
                ],
                [
                    926.097984,
                    556.10112
                ],
                [
                    913.4979840000001,
                    556.10112
                ],
                [
                    907.2,
                    562.4
                ],
                [
                    882.0,
                    562.4
                ],
                [
                    875.697984,
                    568.6988799999999
                ],
                [
                    863.097984,
                    568.6988799999999
                ],
                [
                    844.2,
                    587.59856
                ],
                [
                    831.5999999999999,
                    587.59856
                ],
                [
                    781.2,
                    637.99872
                ],
                [
                    781.2,
                    644.3006399999999
                ],
                [
                    756.0,
                    669.4992
                ],
                [
                    756.0,
                    688.3988800000001
                ],
                [
                    749.697984,
                    694.7008
                ],
                [
                    749.697984,
                    700.99968
                ],
                [
                    737.097984,
                    713.60048
                ],
                [
                    737.097984,
                    719.89936
                ],
                [
                    730.8,
                    726.20128
                ],
                [
                    730.8,
                    738.79904
                ],
                [
                    724.5020159999999,
                    745.10096
                ],
                [
                    724.5020159999999,
                    757.69872
                ],
                [
                    711.897984,
                    770.29952
                ],
                [
                    711.897984,
                    782.9003200000001
                ],
                [
                    705.5999999999999,
                    789.1991999999999
                ],
                [
                    705.5999999999999,
                    902.60032
                ],
                [
                    711.897984,
                    908.8992000000001
                ],
                [
                    724.5020159999999,
                    908.8992000000001
                ],
                [
                    730.8,
                    915.2011200000001
                ],
                [
                    737.097984,
                    915.2011200000001
                ],
                [
                    756.0,
                    934.1007999999999
                ],
                [
                    762.297984,
                    934.1007999999999
                ],
                [
                    768.5999999999999,
                    940.39968
                ],
                [
                    774.897984,
                    940.39968
                ],
                [
                    787.4979840000001,
                    953.00048
                ],
                [
                    793.8,
                    953.00048
                ],
                [
                    800.097984,
                    959.29936
                ],
                [
                    812.697984,
                    959.29936
                ],
                [
                    819.0,
                    953.00048
                ],
                [
                    825.297984,
                    953.00048
                ],
                [
                    850.5020159999999,
                    927.7988799999999
                ],
                [
                    850.5020159999999,
                    908.8992000000001
                ],
                [
                    856.8,
                    902.60032
                ],
                [
                    856.8,
                    896.30144
                ],
                [
                    869.4000000000001,
                    883.7006399999999
                ],
                [
                    888.297984,
                    883.7006399999999
                ],
                [
                    900.897984,
                    896.30144
                ],
                [
                    900.897984,
                    908.8992000000001
                ],
                [
                    907.2,
                    915.2011200000001
                ],
                [
                    907.2,
                    959.29936
                ],
                [
                    913.4979840000001,
                    965.6012800000001
                ],
                [
                    913.4979840000001,
                    971.9001599999999
                ],
                [
                    919.8,
                    978.19904
                ],
                [
                    919.8,
                    984.50096
                ],
                [
                    926.097984,
                    990.79984
                ],
                [
                    926.097984,
                    997.09872
                ],
                [
                    932.4000000000001,
                    1003.4006400000001
                ],
                [
                    932.4000000000001,
                    1022.3003199999999
                ],
                [
                    926.097984,
                    1028.5992
                ],
                [
                    926.097984,
                    1047.4988799999999
                ],
                [
                    919.8,
                    1053.8008
                ],
                [
                    919.8,
                    1060.09968
                ],
                [
                    913.4979840000001,
                    1066.39856
                ],
                [
                    913.4979840000001,
                    1097.89904
                ],
                [
                    919.8,
                    1104.20096
                ],
                [
                    919.8,
                    1110.49984
                ],
                [
                    938.697984,
                    1129.39952
                ],
                [
                    951.297984,
                    1129.39952
                ],
                [
                    957.5999999999999,
                    1123.10064
                ],
                [
                    963.897984,
                    1123.10064
                ],
                [
                    976.4979840000001,
                    1110.49984
                ],
                [
                    982.8,
                    1110.49984
                ],
                [
                    989.097984,
                    1104.20096
                ],
                [
                    1001.697984,
                    1104.20096
                ],
                [
                    1014.3020159999999,
                    1091.60016
                ],
                [
                    1026.902016,
                    1091.60016
                ],
                [
                    1039.4979839999999,
                    1104.20096
                ],
                [
                    1039.4979839999999,
                    1116.79872
                ],
                [
                    1045.8000000000002,
                    1123.10064
                ],
                [
                    1026.902016,
                    1142.0003199999999
                ],
                [
                    1026.902016,
                    1148.2992
                ],
                [
                    1008.0,
                    1167.19888
                ],
                [
                    1008.0,
                    1173.5008
                ],
                [
                    982.8,
                    1198.69936
                ],
                [
                    982.8,
                    1223.90096
                ],
                [
                    976.4979840000001,
                    1230.19984
                ],
                [
                    976.4979840000001,
                    1236.49872
                ],
                [
                    963.897984,
                    1249.09952
                ],
                [
                    963.897984,
                    1255.3984
                ],
                [
                    970.2,
                    1261.70032
                ],
                [
                    970.2,
                    1267.9992
                ],
                [
                    976.4979840000001,
                    1274.30112
                ],
                [
                    976.4979840000001,
                    1280.6000000000001
                ],
                [
                    982.8,
                    1280.6000000000001
                ],
                [
                    989.097984,
                    1286.89888
                ],
                [
                    1033.1999999999998,
                    1286.89888
                ],
                [
                    1039.4979839999999,
                    1280.6000000000001
                ],
                [
                    1045.8000000000002,
                    1280.6000000000001
                ],
                [
                    1052.097984,
                    1274.30112
                ],
                [
                    1058.4,
                    1274.30112
                ],
                [
                    1071.0,
                    1261.70032
                ],
                [
                    1089.897984,
                    1261.70032
                ],
                [
                    1096.1999999999998,
                    1255.3984
                ],
                [
                    1102.5020160000001,
                    1255.3984
                ],
                [
                    1108.8000000000002,
                    1249.09952
                ],
                [
                    1108.8000000000002,
                    1242.80064
                ],
                [
                    1115.097984,
                    1236.49872
                ],
                [
                    1121.4,
                    1236.49872
                ],
                [
                    1127.6979840000001,
                    1230.19984
                ],
                [
                    1127.6979840000001,
                    1223.90096
                ],
                [
                    1134.0,
                    1217.59904
                ],
                [
                    1134.0,
                    1211.30016
                ],
                [
                    1146.6,
                    1198.69936
                ],
                [
                    1140.297984,
                    1192.40048
                ],
                [
                    1140.297984,
                    1148.2992
                ],
                [
                    1146.6,
                    1142.0003199999999
                ],
                [
                    1146.6,
                    1123.10064
                ],
                [
                    1152.897984,
                    1116.79872
                ],
                [
                    1152.897984,
                    1110.49984
                ],
                [
                    1159.1999999999998,
                    1104.20096
                ],
                [
                    1159.1999999999998,
                    1097.89904
                ],
                [
                    1171.8000000000002,
                    1085.3012800000001
                ],
                [
                    1171.8000000000002,
                    1078.99936
                ],
                [
                    1178.097984,
                    1072.70048
                ],
                [
                    1178.097984,
                    1066.39856
                ],
                [
                    1184.4,
                    1060.09968
                ],
                [
                    1184.4,
                    1053.8008
                ],
                [
                    1215.897984,
                    1022.3003199999999
                ],
                [
                    1215.897984,
                    1016.0014399999999
                ],
                [
                    1222.1999999999998,
                    1009.69952
                ],
                [
                    1222.1999999999998,
                    1003.4006400000001
                ],
                [
                    1228.5020160000001,
                    997.09872
                ],
                [
                    1228.5020160000001,
                    990.79984
                ],
                [
                    1234.8000000000002,
                    984.50096
                ],
                [
                    1234.8000000000002,
                    971.9001599999999
                ],
                [
                    1241.097984,
                    965.6012800000001
                ],
                [
                    1241.097984,
                    953.00048
                ],
                [
                    1247.4,
                    946.69856
                ],
                [
                    1247.4,
                    927.7988799999999
                ],
                [
                    1253.6979840000001,
                    921.4999999999999
                ],
                [
                    1253.6979840000001,
                    883.7006399999999
                ],
                [
                    1260.0,
                    877.3987199999999
                ],
                [
                    1260.0,
                    833.3004800000001
                ],
                [
                    1266.297984,
                    826.9985599999999
                ],
                [
                    1266.297984,
                    789.1991999999999
                ],
                [
                    1272.6,
                    782.9003200000001
                ],
                [
                    1272.6,
                    757.69872
                ],
                [
                    1278.897984,
                    751.39984
                ],
                [
                    1278.897984,
                    732.50016
                ],
                [
                    1285.1999999999998,
                    726.20128
                ],
                [
                    1285.1999999999998,
                    707.2985600000001
                ],
                [
                    1291.4979839999999,
                    700.99968
                ],
                [
                    1291.4979839999999,
                    644.3006399999999
                ],
                [
                    1285.1999999999998,
                    637.99872
                ],
                [
                    1285.1999999999998,
                    612.80016
                ],
                [
                    1278.897984,
                    606.50128
                ],
                [
                    1278.897984,
                    593.90048
                ],
                [
                    1272.6,
                    587.59856
                ],
                [
                    1272.6,
                    581.29968
                ],
                [
                    1260.0,
                    568.6988799999999
                ],
                [
                    1260.0,
                    562.4
                ],
                [
                    1253.6979840000001,
                    556.10112
                ],
                [
                    1253.6979840000001,
                    549.7991999999999
                ],
                [
                    1222.1999999999998,
                    518.29872
                ],
                [
                    1215.897984,
                    518.29872
                ],
                [
                    1209.6,
                    511.99983999999995
                ]
            ],
            "group_id": 0,
            "shape_type": "polygon",
            "flags": {}
        }
    ],
    "imagePath": "CAS003_CAS0000226_stacked_02_H.png",
    "imageData": null,
    "imageHeight": 3040,
    "imageWidth": 4032,
    "lineColor": [
        0,
        255,
        0,
        128
    ],
    "fillColor": [
        255,
        0,
        0,
        128
    ]
}