{
    "version": "4.5.7",
    "flags": {},
    "shapes": [
        {
            "label": "abdomen",
            "points": [
                [
                    2079.0,
                    1167.19888
                ],
                [
                    2072.697984,
                    1173.5008
                ],
                [
                    2066.3999999999996,
                    1173.5008
                ],
                [
                    2066.3999999999996,
                    1179.79968
                ],
                [
                    2053.8,
                    1192.40048
                ],
                [
                    2047.497984,
                    1192.40048
                ],
                [
                    2016.0,
                    1223.90096
                ],
                [
                    2016.0,
                    1312.10048
                ],
                [
                    2022.2979839999998,
                    1318.3993600000001
                ],
                [
                    2022.2979839999998,
                    1331.00016
                ],
                [
                    2047.497984,
                    1356.19872
                ],
                [
                    2047.497984,
                    1362.50064
                ],
                [
                    2072.697984,
                    1387.6992
                ],
                [
                    2072.697984,
                    1394.00112
                ],
                [
                    2079.0,
                    1394.00112
                ],
                [
                    2085.302016,
                    1400.3
                ],
                [
                    2085.302016,
                    1406.59888
                ],
                [
                    2116.8,
                    1438.09936
                ],
                [
                    2123.097984,
                    1438.09936
                ],
                [
                    2148.297984,
                    1463.30096
                ],
                [
                    2154.6000000000004,
                    1463.30096
                ],
                [
                    2198.697984,
                    1507.3992
                ],
                [
                    2205.0,
                    1507.3992
                ],
                [
                    2242.8,
                    1545.19856
                ],
                [
                    2249.097984,
                    1545.19856
                ],
                [
                    2261.697984,
                    1557.7993599999998
                ],
                [
                    2268.0,
                    1557.7993599999998
                ],
                [
                    2274.297984,
                    1564.10128
                ],
                [
                    2286.897984,
                    1564.10128
                ],
                [
                    2293.2,
                    1570.4001600000001
                ],
                [
                    2299.497984,
                    1570.4001600000001
                ],
                [
                    2305.8,
                    1576.69904
                ],
                [
                    2312.097984,
                    1576.69904
                ],
                [
                    2318.3999999999996,
                    1583.0009599999998
                ],
                [
                    2324.697984,
                    1583.0009599999998
                ],
                [
                    2331.0,
                    1589.2998400000001
                ],
                [
                    2349.897984,
                    1589.2998400000001
                ],
                [
                    2356.2,
                    1595.59872
                ],
                [
                    2362.502016,
                    1595.59872
                ],
                [
                    2368.8,
                    1601.90064
                ],
                [
                    2375.097984,
                    1601.90064
                ],
                [
                    2381.3999999999996,
                    1608.19952
                ],
                [
                    2394.0,
                    1608.19952
                ],
                [
                    2400.297984,
                    1614.4984000000002
                ],
                [
                    2412.897984,
                    1614.4984000000002
                ],
                [
                    2419.2,
                    1620.80032
                ],
                [
                    2425.497984,
                    1620.80032
                ],
                [
                    2444.3999999999996,
                    1639.7
                ],
                [
                    2457.0,
                    1639.7
                ],
                [
                    2463.297984,
                    1645.99888
                ],
                [
                    2469.6000000000004,
                    1645.99888
                ],
                [
                    2482.2,
                    1658.5996799999998
                ],
                [
                    2494.8,
                    1658.5996799999998
                ],
                [
                    2501.097984,
                    1664.89856
                ],
                [
                    2646.0,
                    1664.89856
                ],
                [
                    2652.297984,
                    1658.5996799999998
                ],
                [
                    2658.6000000000004,
                    1658.5996799999998
                ],
                [
                    2683.8,
                    1633.40112
                ],
                [
                    2683.8,
                    1627.0991999999999
                ],
                [
                    2690.097984,
                    1620.80032
                ],
                [
                    2690.097984,
                    1545.19856
                ],
                [
                    2683.8,
                    1538.89968
                ],
                [
                    2683.8,
                    1526.2988799999998
                ],
                [
                    2671.2,
                    1513.70112
                ],
                [
                    2671.2,
                    1507.3992
                ],
                [
                    2664.897984,
                    1501.10032
                ],
                [
                    2664.897984,
                    1475.89872
                ],
                [
                    2639.697984,
                    1450.70016
                ],
                [
                    2639.697984,
                    1431.8004799999999
                ],
                [
                    2633.3999999999996,
                    1425.49856
                ],
                [
                    2633.3999999999996,
                    1419.19968
                ],
                [
                    2620.8,
                    1406.59888
                ],
                [
                    2620.8,
                    1400.3
                ],
                [
                    2614.502016,
                    1394.00112
                ],
                [
                    2614.502016,
                    1387.6992
                ],
                [
                    2608.2,
                    1381.40032
                ],
                [
                    2608.2,
                    1375.1014400000001
                ],
                [
                    2601.897984,
                    1375.1014400000001
                ],
                [
                    2583.0,
                    1356.19872
                ],
                [
                    2583.0,
                    1349.89984
                ],
                [
                    2576.697984,
                    1349.89984
                ],
                [
                    2564.097984,
                    1337.2990399999999
                ],
                [
                    2557.8,
                    1337.2990399999999
                ],
                [
                    2538.897984,
                    1318.3993600000001
                ],
                [
                    2532.6000000000004,
                    1318.3993600000001
                ],
                [
                    2526.297984,
                    1312.10048
                ],
                [
                    2520.0,
                    1312.10048
                ],
                [
                    2513.697984,
                    1305.79856
                ],
                [
                    2513.697984,
                    1299.49968
                ],
                [
                    2507.3999999999996,
                    1293.2008
                ],
                [
                    2494.8,
                    1293.2008
                ],
                [
                    2488.502016,
                    1286.89888
                ],
                [
                    2482.2,
                    1286.89888
                ],
                [
                    2457.0,
                    1261.70032
                ],
                [
                    2450.697984,
                    1261.70032
                ],
                [
                    2431.8,
                    1242.80064
                ],
                [
                    2425.497984,
                    1242.80064
                ],
                [
                    2406.6000000000004,
                    1223.90096
                ],
                [
                    2400.297984,
                    1223.90096
                ],
                [
                    2394.0,
                    1217.59904
                ],
                [
                    2381.3999999999996,
                    1217.59904
                ],
                [
                    2375.097984,
                    1211.30016
                ],
                [
                    2368.8,
                    1211.30016
                ],
                [
                    2349.897984,
                    1192.40048
                ],
                [
                    2337.297984,
                    1192.40048
                ],
                [
                    2331.0,
                    1186.0985600000001
                ],
                [
                    2324.697984,
                    1186.0985600000001
                ],
                [
                    2318.3999999999996,
                    1179.79968
                ],
                [
                    2312.097984,
                    1179.79968
                ],
                [
                    2305.8,
                    1173.5008
                ],
                [
                    2286.897984,
                    1173.5008
                ],
                [
                    2280.6000000000004,
                    1167.19888
                ]
            ],
            "group_id": 1,
            "shape_type": "polygon",
            "flags": {}
        },
        {
            "label": "head",
            "points": [
                [
                    1341.897984,
                    1167.19888
                ],
                [
                    1335.6,
                    1173.5008
                ],
                [
                    1335.6,
                    1179.79968
                ],
                [
                    1323.0,
                    1192.40048
                ],
                [
                    1316.6979840000001,
                    1192.40048
                ],
                [
                    1310.4,
                    1198.69936
                ],
                [
                    1310.4,
                    1205.00128
                ],
                [
                    1285.1999999999998,
                    1230.19984
                ],
                [
                    1285.1999999999998,
                    1267.9992
                ],
                [
                    1278.897984,
                    1274.30112
                ],
                [
                    1278.897984,
                    1280.6000000000001
                ],
                [
                    1260.0,
                    1299.49968
                ],
                [
                    1260.0,
                    1356.19872
                ],
                [
                    1253.6979840000001,
                    1362.50064
                ],
                [
                    1253.6979840000001,
                    1368.79952
                ],
                [
                    1241.097984,
                    1381.40032
                ],
                [
                    1241.097984,
                    1387.6992
                ],
                [
                    1234.8000000000002,
                    1394.00112
                ],
                [
                    1234.8000000000002,
                    1501.10032
                ],
                [
                    1241.097984,
                    1507.3992
                ],
                [
                    1241.097984,
                    1513.70112
                ],
                [
                    1266.297984,
                    1538.89968
                ],
                [
                    1272.6,
                    1538.89968
                ],
                [
                    1285.1999999999998,
                    1551.50048
                ],
                [
                    1285.1999999999998,
                    1557.7993599999998
                ],
                [
                    1291.4979839999999,
                    1564.10128
                ],
                [
                    1297.8000000000002,
                    1564.10128
                ],
                [
                    1310.4,
                    1576.69904
                ],
                [
                    1310.4,
                    1583.0009599999998
                ],
                [
                    1316.6979840000001,
                    1589.2998400000001
                ],
                [
                    1323.0,
                    1589.2998400000001
                ],
                [
                    1348.1999999999998,
                    1614.4984000000002
                ],
                [
                    1354.5020160000001,
                    1614.4984000000002
                ],
                [
                    1373.4,
                    1633.40112
                ],
                [
                    1379.6979840000001,
                    1633.40112
                ],
                [
                    1386.0,
                    1639.7
                ],
                [
                    1392.297984,
                    1639.7
                ],
                [
                    1398.6,
                    1645.99888
                ],
                [
                    1404.897984,
                    1645.99888
                ],
                [
                    1417.4979839999999,
                    1658.5996799999998
                ],
                [
                    1423.8000000000002,
                    1658.5996799999998
                ],
                [
                    1430.097984,
                    1664.89856
                ],
                [
                    1455.297984,
                    1664.89856
                ],
                [
                    1461.6,
                    1658.5996799999998
                ],
                [
                    1467.897984,
                    1658.5996799999998
                ],
                [
                    1480.5020160000001,
                    1645.99888
                ],
                [
                    1486.8000000000002,
                    1645.99888
                ],
                [
                    1505.6979840000001,
                    1627.0991999999999
                ],
                [
                    1505.6979840000001,
                    1620.80032
                ],
                [
                    1512.0,
                    1614.4984000000002
                ],
                [
                    1512.0,
                    1608.19952
                ],
                [
                    1518.297984,
                    1601.90064
                ],
                [
                    1518.297984,
                    1595.59872
                ],
                [
                    1524.6,
                    1589.2998400000001
                ],
                [
                    1524.6,
                    1583.0009599999998
                ],
                [
                    1530.897984,
                    1576.69904
                ],
                [
                    1530.897984,
                    1557.7993599999998
                ],
                [
                    1549.8000000000002,
                    1538.89968
                ],
                [
                    1556.097984,
                    1538.89968
                ],
                [
                    1562.4,
                    1532.6008
                ],
                [
                    1568.6979840000001,
                    1532.6008
                ],
                [
                    1575.0,
                    1526.2988799999998
                ],
                [
                    1575.0,
                    1513.70112
                ],
                [
                    1581.297984,
                    1507.3992
                ],
                [
                    1581.297984,
                    1501.10032
                ],
                [
                    1575.0,
                    1494.80144
                ],
                [
                    1575.0,
                    1482.20064
                ],
                [
                    1562.4,
                    1469.5998399999999
                ],
                [
                    1562.4,
                    1463.30096
                ],
                [
                    1556.097984,
                    1456.99904
                ],
                [
                    1556.097984,
                    1450.70016
                ],
                [
                    1549.8000000000002,
                    1444.40128
                ],
                [
                    1549.8000000000002,
                    1438.09936
                ],
                [
                    1537.1999999999998,
                    1425.49856
                ],
                [
                    1537.1999999999998,
                    1419.19968
                ],
                [
                    1530.897984,
                    1412.9008000000001
                ],
                [
                    1530.897984,
                    1406.59888
                ],
                [
                    1524.6,
                    1400.3
                ],
                [
                    1524.6,
                    1387.6992
                ],
                [
                    1518.297984,
                    1381.40032
                ],
                [
                    1518.297984,
                    1375.1014400000001
                ],
                [
                    1505.6979840000001,
                    1362.50064
                ],
                [
                    1505.6979840000001,
                    1356.19872
                ],
                [
                    1499.4,
                    1349.89984
                ],
                [
                    1499.4,
                    1343.60096
                ],
                [
                    1486.8000000000002,
                    1331.00016
                ],
                [
                    1486.8000000000002,
                    1318.3993600000001
                ],
                [
                    1480.5020160000001,
                    1312.10048
                ],
                [
                    1480.5020160000001,
                    1286.89888
                ],
                [
                    1474.1999999999998,
                    1280.6000000000001
                ],
                [
                    1474.1999999999998,
                    1255.3984
                ],
                [
                    1467.897984,
                    1249.09952
                ],
                [
                    1467.897984,
                    1236.49872
                ],
                [
                    1461.6,
                    1230.19984
                ],
                [
                    1461.6,
                    1217.59904
                ],
                [
                    1455.297984,
                    1211.30016
                ],
                [
                    1455.297984,
                    1198.69936
                ],
                [
                    1423.8000000000002,
                    1167.19888
                ]
            ],
            "group_id": 0,
            "shape_type": "polygon",
            "flags": {}
        },
        {
            "label": "thorax",
            "points": [
                [
                    1669.4979839999999,
                    1066.39856
                ],
                [
                    1663.1999999999998,
                    1072.70048
                ],
                [
                    1656.897984,
                    1072.70048
                ],
                [
                    1644.297984,
                    1085.3012800000001
                ],
                [
                    1638.0,
                    1085.3012800000001
                ],
                [
                    1631.6979840000001,
                    1091.60016
                ],
                [
                    1619.097984,
                    1091.60016
                ],
                [
                    1612.8000000000002,
                    1097.89904
                ],
                [
                    1612.8000000000002,
                    1104.20096
                ],
                [
                    1600.1999999999998,
                    1116.79872
                ],
                [
                    1587.6,
                    1116.79872
                ],
                [
                    1581.297984,
                    1123.10064
                ],
                [
                    1575.0,
                    1123.10064
                ],
                [
                    1562.4,
                    1135.7014399999998
                ],
                [
                    1556.097984,
                    1135.7014399999998
                ],
                [
                    1549.8000000000002,
                    1142.0003199999999
                ],
                [
                    1543.4979839999999,
                    1142.0003199999999
                ],
                [
                    1518.297984,
                    1167.19888
                ],
                [
                    1512.0,
                    1167.19888
                ],
                [
                    1505.6979840000001,
                    1173.5008
                ],
                [
                    1499.4,
                    1173.5008
                ],
                [
                    1493.097984,
                    1179.79968
                ],
                [
                    1493.097984,
                    1186.0985600000001
                ],
                [
                    1486.8000000000002,
                    1192.40048
                ],
                [
                    1486.8000000000002,
                    1324.70128
                ],
                [
                    1493.097984,
                    1331.00016
                ],
                [
                    1493.097984,
                    1337.2990399999999
                ],
                [
                    1512.0,
                    1356.19872
                ],
                [
                    1512.0,
                    1362.50064
                ],
                [
                    1518.297984,
                    1368.79952
                ],
                [
                    1524.6,
                    1368.79952
                ],
                [
                    1530.897984,
                    1375.1014400000001
                ],
                [
                    1530.897984,
                    1381.40032
                ],
                [
                    1537.1999999999998,
                    1387.6992
                ],
                [
                    1537.1999999999998,
                    1400.3
                ],
                [
                    1543.4979839999999,
                    1406.59888
                ],
                [
                    1543.4979839999999,
                    1412.9008000000001
                ],
                [
                    1556.097984,
                    1425.49856
                ],
                [
                    1556.097984,
                    1431.8004799999999
                ],
                [
                    1562.4,
                    1438.09936
                ],
                [
                    1562.4,
                    1444.40128
                ],
                [
                    1568.6979840000001,
                    1450.70016
                ],
                [
                    1568.6979840000001,
                    1456.99904
                ],
                [
                    1587.6,
                    1475.89872
                ],
                [
                    1587.6,
                    1482.20064
                ],
                [
                    1600.1999999999998,
                    1494.80144
                ],
                [
                    1606.5020160000001,
                    1494.80144
                ],
                [
                    1631.6979840000001,
                    1520.0
                ],
                [
                    1638.0,
                    1520.0
                ],
                [
                    1650.6,
                    1532.6008
                ],
                [
                    1663.1999999999998,
                    1532.6008
                ],
                [
                    1669.4979839999999,
                    1538.89968
                ],
                [
                    1707.297984,
                    1538.89968
                ],
                [
                    1713.6,
                    1545.19856
                ],
                [
                    1732.5020160000001,
                    1545.19856
                ],
                [
                    1745.097984,
                    1557.7993599999998
                ],
                [
                    1757.6979840000001,
                    1557.7993599999998
                ],
                [
                    1764.0,
                    1564.10128
                ],
                [
                    1776.6,
                    1564.10128
                ],
                [
                    1782.897984,
                    1570.4001600000001
                ],
                [
                    1789.1999999999998,
                    1570.4001600000001
                ],
                [
                    1795.4979839999999,
                    1576.69904
                ],
                [
                    1801.8000000000002,
                    1576.69904
                ],
                [
                    1808.097984,
                    1583.0009599999998
                ],
                [
                    1877.4,
                    1583.0009599999998
                ],
                [
                    1883.6979840000001,
                    1576.69904
                ],
                [
                    1890.0,
                    1576.69904
                ],
                [
                    1890.0,
                    1488.49952
                ],
                [
                    1896.297984,
                    1482.20064
                ],
                [
                    1896.297984,
                    1400.3
                ],
                [
                    1890.0,
                    1394.00112
                ],
                [
                    1890.0,
                    1381.40032
                ],
                [
                    1883.6979840000001,
                    1375.1014400000001
                ],
                [
                    1883.6979840000001,
                    1362.50064
                ],
                [
                    1877.4,
                    1356.19872
                ],
                [
                    1877.4,
                    1349.89984
                ],
                [
                    1864.8000000000002,
                    1337.2990399999999
                ],
                [
                    1864.8000000000002,
                    1331.00016
                ],
                [
                    1858.4979839999999,
                    1324.70128
                ],
                [
                    1858.4979839999999,
                    1299.49968
                ],
                [
                    1839.6,
                    1280.6000000000001
                ],
                [
                    1839.6,
                    1274.30112
                ],
                [
                    1833.297984,
                    1267.9992
                ],
                [
                    1833.297984,
                    1249.09952
                ],
                [
                    1827.0,
                    1242.80064
                ],
                [
                    1820.6979840000001,
                    1242.80064
                ],
                [
                    1808.097984,
                    1230.19984
                ],
                [
                    1808.097984,
                    1223.90096
                ],
                [
                    1776.6,
                    1192.40048
                ],
                [
                    1776.6,
                    1186.0985600000001
                ],
                [
                    1764.0,
                    1173.5008
                ],
                [
                    1764.0,
                    1160.9
                ],
                [
                    1757.6979840000001,
                    1154.60112
                ],
                [
                    1757.6979840000001,
                    1142.0003199999999
                ],
                [
                    1764.0,
                    1135.7014399999998
                ],
                [
                    1764.0,
                    1123.10064
                ],
                [
                    1770.297984,
                    1116.79872
                ],
                [
                    1776.6,
                    1116.79872
                ],
                [
                    1782.897984,
                    1110.49984
                ],
                [
                    1801.8000000000002,
                    1110.49984
                ],
                [
                    1808.097984,
                    1104.20096
                ],
                [
                    1814.4,
                    1104.20096
                ],
                [
                    1820.6979840000001,
                    1097.89904
                ],
                [
                    1833.297984,
                    1097.89904
                ],
                [
                    1839.6,
                    1091.60016
                ],
                [
                    1877.4,
                    1091.60016
                ],
                [
                    1883.6979840000001,
                    1085.3012800000001
                ],
                [
                    1890.0,
                    1085.3012800000001
                ],
                [
                    1896.297984,
                    1078.99936
                ],
                [
                    1896.297984,
                    1072.70048
                ],
                [
                    1827.0,
                    1072.70048
                ],
                [
                    1820.6979840000001,
                    1066.39856
                ]
            ],
            "group_id": 2,
            "shape_type": "polygon",
            "flags": {}
        }
    ],
    "imagePath": "CAS005_CAS0000409_stacked_01_H.png",
    "imageData": null,
    "imageHeight": 3040,
    "imageWidth": 4032,
    "lineColor": [
        0,
        255,
        0,
        128
    ],
    "fillColor": [
        255,
        0,
        0,
        128
    ]
}